{"gxl":{"$":{"xmlns:xlink":"http://www.w3.org/1999/xlink"},"graph":[{"$":{"id":"AP1_0078","edgeids":"false","edgemode":"undirected"},"node":[{"$":{"id":"_0"},"attr":[{"$":{"name":"x"},"float":["0.68719"]},{"$":{"name":"y"},"float":["0.586837"]}]},{"$":{"id":"_1"},"attr":[{"$":{"name":"x"},"float":["1.8261"]},{"$":{"name":"y"},"float":["2.40167"]}]},{"$":{"id":"_2"},"attr":[{"$":{"name":"x"},"float":["2.2429"]},{"$":{"name":"y"},"float":["0.944571"]}]},{"$":{"id":"_3"},"attr":[{"$":{"name":"x"},"float":["0.788269"]},{"$":{"name":"y"},"float":["1.07962"]}]},{"$":{"id":"_4"},"attr":[{"$":{"name":"x"},"float":["2.12"]},{"$":{"name":"y"},"float":["1.49"]}]},{"$":{"id":"_5"},"attr":[{"$":{"name":"x"},"float":["1.08492"]},{"$":{"name":"y"},"float":["0.494858"]}]}],"edge":[{"$":{"from":"_0","to":"_1"}},{"$":{"from":"_0","to":"_2"}},{"$":{"from":"_1","to":"_2"}},{"$":{"from":"_1","to":"_4"}},{"$":{"from":"_2","to":"_4"}},{"$":{"from":"_3","to":"_4"}},{"$":{"from":"_4","to":"_5"}}]}]}}