{"gxl":{"$":{"xmlns:xlink":"http://www.w3.org/1999/xlink"},"graph":[{"$":{"id":"EP1_0005","edgeids":"false","edgemode":"undirected"},"node":[{"$":{"id":"_0"},"attr":[{"$":{"name":"x"},"float":["1.60354"]},{"$":{"name":"y"},"float":["2.89227"]}]},{"$":{"id":"_1"},"attr":[{"$":{"name":"x"},"float":["2.07333"]},{"$":{"name":"y"},"float":["0.833336"]}]},{"$":{"id":"_2"},"attr":[{"$":{"name":"x"},"float":["1.24558"]},{"$":{"name":"y"},"float":["0.672563"]}]},{"$":{"id":"_3"},"attr":[{"$":{"name":"x"},"float":["0.73"]},{"$":{"name":"y"},"float":["2.73"]}]},{"$":{"id":"_4"},"attr":[{"$":{"name":"x"},"float":["1.13575"]},{"$":{"name":"y"},"float":["1.56964"]}]},{"$":{"id":"_5"},"attr":[{"$":{"name":"x"},"float":["2.01468"]},{"$":{"name":"y"},"float":["1.10979"]}]},{"$":{"id":"_6"},"attr":[{"$":{"name":"x"},"float":["2.09082"]},{"$":{"name":"y"},"float":["0.150861"]}]}],"edge":[{"$":{"from":"_0","to":"_3"}},{"$":{"from":"_0","to":"_4"}},{"$":{"from":"_1","to":"_2"}},{"$":{"from":"_1","to":"_3"}},{"$":{"from":"_2","to":"_3"}},{"$":{"from":"_2","to":"_5"}},{"$":{"from":"_3","to":"_6"}},{"$":{"from":"_4","to":"_5"}}]}]}}