{"gxl":{"$":{"xmlns:xlink":"http://www.w3.org/1999/xlink"},"graph":[{"$":{"id":"HP1_0118","edgeids":"false","edgemode":"undirected"},"node":[{"$":{"id":"_0"},"attr":[{"$":{"name":"x"},"float":["1.02601"]},{"$":{"name":"y"},"float":["2.84037"]}]},{"$":{"id":"_1"},"attr":[{"$":{"name":"x"},"float":["0.692595"]},{"$":{"name":"y"},"float":["0.519457"]}]},{"$":{"id":"_2"},"attr":[{"$":{"name":"x"},"float":["2.43464"]},{"$":{"name":"y"},"float":["0.6883"]}]},{"$":{"id":"_3"},"attr":[{"$":{"name":"x"},"float":["2.92597"]},{"$":{"name":"y"},"float":["2.75493"]}]},{"$":{"id":"_4"},"attr":[{"$":{"name":"x"},"float":["0.732582"]},{"$":{"name":"y"},"float":["1.75333"]}]},{"$":{"id":"_5"},"attr":[{"$":{"name":"x"},"float":["1.89933"]},{"$":{"name":"y"},"float":["1.49137"]}]}],"edge":[{"$":{"from":"_0","to":"_1"}},{"$":{"from":"_0","to":"_5"}},{"$":{"from":"_1","to":"_2"}},{"$":{"from":"_2","to":"_3"}},{"$":{"from":"_2","to":"_4"}},{"$":{"from":"_4","to":"_5"}}]}]}}