{"gxl":{"$":{"xmlns:xlink":"http://www.w3.org/1999/xlink"},"graph":[{"$":{"id":"IP1_0032","edgeids":"false","edgemode":"undirected"},"node":[{"$":{"id":"_0"},"attr":[{"$":{"name":"x"},"float":["1.19327"]},{"$":{"name":"y"},"float":["3.62161"]}]},{"$":{"id":"_1"},"attr":[{"$":{"name":"x"},"float":["1.5"]},{"$":{"name":"y"},"float":["0.49"]}]},{"$":{"id":"_2"},"attr":[{"$":{"name":"x"},"float":["2.47464"]},{"$":{"name":"y"},"float":["0.0806258"]}]}],"edge":[{"$":{"from":"_0","to":"_1"}},{"$":{"from":"_1","to":"_2"}}]}]}}