{"gxl":{"$":{"xmlns:xlink":"http://www.w3.org/1999/xlink"},"graph":[{"$":{"id":"MP1_0122","edgeids":"false","edgemode":"undirected"},"node":[{"$":{"id":"_0"},"attr":[{"$":{"name":"x"},"float":["1.49697"]},{"$":{"name":"y"},"float":["1.76397"]}]},{"$":{"id":"_1"},"attr":[{"$":{"name":"x"},"float":["2.37386"]},{"$":{"name":"y"},"float":["3.2229"]}]},{"$":{"id":"_2"},"attr":[{"$":{"name":"x"},"float":["2.90064"]},{"$":{"name":"y"},"float":["0.996869"]}]},{"$":{"id":"_3"},"attr":[{"$":{"name":"x"},"float":["1.06418"]},{"$":{"name":"y"},"float":["0.154168"]}]},{"$":{"id":"_4"},"attr":[{"$":{"name":"x"},"float":["0.916054"]},{"$":{"name":"y"},"float":["3.04612"]}]},{"$":{"id":"_5"},"attr":[{"$":{"name":"x"},"float":["1.7500189613908912"]},{"$":{"name":"y"},"float":["2.1849814395671214"]}]},{"$":{"id":"_6"},"attr":[{"$":{"name":"x"},"float":["1.8755672459180657"]},{"$":{"name":"y"},"float":["2.055342337197359"]}]}],"edge":[{"$":{"from":"_0","to":"_3"}},{"$":{"from":"_0","to":"_4"}},{"$":{"from":"_1","to":"_2"}},{"$":{"from":"_3","to":"_4"}},{"$":{"from":"_0","to":"_5"}},{"$":{"from":"_5","to":"_1"}},{"$":{"from":"_5","to":"_4"}},{"$":{"from":"_1","to":"_6"}},{"$":{"from":"_6","to":"_3"}},{"$":{"from":"_2","to":"_6"}},{"$":{"from":"_6","to":"_5"}}]}]}}