{"gxl":{"$":{"xmlns:xlink":"http://www.w3.org/1999/xlink"},"graph":[{"$":{"id":"TP1_0068","edgeids":"false","edgemode":"undirected"},"node":[{"$":{"id":"_0"},"attr":[{"$":{"name":"x"},"float":["0.394179"]},{"$":{"name":"y"},"float":["2.991"]}]},{"$":{"id":"_1"},"attr":[{"$":{"name":"x"},"float":["2.39"]},{"$":{"name":"y"},"float":["2.81"]}]},{"$":{"id":"_2"},"attr":[{"$":{"name":"x"},"float":["1.55068"]},{"$":{"name":"y"},"float":["0.800685"]}]},{"$":{"id":"_3"},"attr":[{"$":{"name":"x"},"float":["1.48889"]},{"$":{"name":"y"},"float":["3.44969"]}]},{"$":{"id":"_4"},"attr":[{"$":{"name":"x"},"float":["0.34718"]},{"$":{"name":"y"},"float":["2.09873"]}]},{"$":{"id":"_5"},"attr":[{"$":{"name":"x"},"float":["1.5019326248540332"]},{"$":{"name":"y"},"float":["2.8905383824007362"]}]},{"$":{"id":"_6"},"attr":[{"$":{"name":"x"},"float":["1.510950501171285"]},{"$":{"name":"y"},"float":["2.5039321442751197"]}]}],"edge":[{"$":{"from":"_0","to":"_3"}},{"$":{"from":"_0","to":"_5"}},{"$":{"from":"_5","to":"_1"}},{"$":{"from":"_5","to":"_3"}},{"$":{"from":"_1","to":"_6"}},{"$":{"from":"_6","to":"_4"}},{"$":{"from":"_2","to":"_6"}},{"$":{"from":"_6","to":"_5"}}]}]}}