{"gxl":{"$":{"xmlns:xlink":"http://www.w3.org/1999/xlink"},"graph":[{"$":{"id":"XP1_0148","edgeids":"false","edgemode":"undirected"},"node":[{"$":{"id":"_0"},"attr":[{"$":{"name":"x"},"float":["2.02074"]},{"$":{"name":"y"},"float":["3.25347"]}]},{"$":{"id":"_1"},"attr":[{"$":{"name":"x"},"float":["0.812426"]},{"$":{"name":"y"},"float":["2.76844"]}]},{"$":{"id":"_2"},"attr":[{"$":{"name":"x"},"float":["0.0220977"]},{"$":{"name":"y"},"float":["0.440785"]}]},{"$":{"id":"_3"},"attr":[{"$":{"name":"x"},"float":["2.20483"]},{"$":{"name":"y"},"float":["0.654449"]}]}],"edge":[{"$":{"from":"_0","to":"_2"}},{"$":{"from":"_1","to":"_3"}}]}]}}