{"gxl":{"$":{"xmlns:xlink":"http://www.w3.org/1999/xlink"},"graph":[{"$":{"id":"AP1_0006","edgeids":"false","edgemode":"undirected"},"node":[{"$":{"id":"_0"},"attr":[{"$":{"name":"x"},"float":["0.664089"]},{"$":{"name":"y"},"float":["0.644549"]}]},{"$":{"id":"_1"},"attr":[{"$":{"name":"x"},"float":["1.47603"]},{"$":{"name":"y"},"float":["2.38832"]}]},{"$":{"id":"_2"},"attr":[{"$":{"name":"x"},"float":["2.37281"]},{"$":{"name":"y"},"float":["0.791548"]}]},{"$":{"id":"_3"},"attr":[{"$":{"name":"x"},"float":["0.834845"]},{"$":{"name":"y"},"float":["1.56635"]}]},{"$":{"id":"_4"},"attr":[{"$":{"name":"x"},"float":["2.13221"]},{"$":{"name":"y"},"float":["1.57387"]}]},{"$":{"id":"_5"},"attr":[{"$":{"name":"x"},"float":["1.0940007785902304"]},{"$":{"name":"y"},"float":["1.5678521612691867"]}]},{"$":{"id":"_6"},"attr":[{"$":{"name":"x"},"float":["1.9340868345304698"]},{"$":{"name":"y"},"float":["1.572721605982641"]}]}],"edge":[{"$":{"from":"_0","to":"_5"}},{"$":{"from":"_5","to":"_1"}},{"$":{"from":"_3","to":"_5"}},{"$":{"from":"_1","to":"_6"}},{"$":{"from":"_6","to":"_2"}},{"$":{"from":"_5","to":"_6"}},{"$":{"from":"_6","to":"_4"}}]}]}}