{"gxl":{"$":{"xmlns:xlink":"http://www.w3.org/1999/xlink"},"graph":[{"$":{"id":"EP1_0076","edgeids":"false","edgemode":"undirected"},"node":[{"$":{"id":"_0"},"attr":[{"$":{"name":"x"},"float":["2.26621"]},{"$":{"name":"y"},"float":["2.65762"]}]},{"$":{"id":"_1"},"attr":[{"$":{"name":"x"},"float":["2.19806"]},{"$":{"name":"y"},"float":["0.783417"]}]},{"$":{"id":"_2"},"attr":[{"$":{"name":"x"},"float":["0.796461"]},{"$":{"name":"y"},"float":["0.790863"]}]},{"$":{"id":"_3"},"attr":[{"$":{"name":"x"},"float":["0.673256"]},{"$":{"name":"y"},"float":["2.65589"]}]},{"$":{"id":"_4"},"attr":[{"$":{"name":"x"},"float":["0.555813"]},{"$":{"name":"y"},"float":["1.8339"]}]},{"$":{"id":"_5"},"attr":[{"$":{"name":"x"},"float":["1.90234"]},{"$":{"name":"y"},"float":["1.65562"]}]},{"$":{"id":"_6"},"attr":[{"$":{"name":"x"},"float":["0.7290726427219438"]},{"$":{"name":"y"},"float":["1.8109604457953923"]}]}],"edge":[{"$":{"from":"_0","to":"_3"}},{"$":{"from":"_1","to":"_2"}},{"$":{"from":"_2","to":"_6"}},{"$":{"from":"_6","to":"_3"}},{"$":{"from":"_4","to":"_6"}},{"$":{"from":"_6","to":"_5"}}]}]}}