{"gxl":{"$":{"xmlns:xlink":"http://www.w3.org/1999/xlink"},"graph":[{"$":{"id":"FP1_0133","edgeids":"false","edgemode":"undirected"},"node":[{"$":{"id":"_0"},"attr":[{"$":{"name":"x"},"float":["0.833183"]},{"$":{"name":"y"},"float":["2.76584"]}]},{"$":{"id":"_1"},"attr":[{"$":{"name":"x"},"float":["0.704998"]},{"$":{"name":"y"},"float":["0.663787"]}]},{"$":{"id":"_2"},"attr":[{"$":{"name":"x"},"float":["0.52"]},{"$":{"name":"y"},"float":["1.77"]}]},{"$":{"id":"_3"},"attr":[{"$":{"name":"x"},"float":["1.58587"]},{"$":{"name":"y"},"float":["1.67701"]}]},{"$":{"id":"_4"},"attr":[{"$":{"name":"x"},"float":["2.1096"]},{"$":{"name":"y"},"float":["2.83031"]}]},{"$":{"id":"_5"},"attr":[{"$":{"name":"x"},"float":["0.305839"]},{"$":{"name":"y"},"float":["1.97122"]}]},{"$":{"id":"_6"},"attr":[{"$":{"name":"x"},"float":["0.7711198199673384"]},{"$":{"name":"y"},"float":["1.748091482020544"]}]}],"edge":[{"$":{"from":"_0","to":"_4"}},{"$":{"from":"_2","to":"_5"}},{"$":{"from":"_0","to":"_6"}},{"$":{"from":"_6","to":"_1"}},{"$":{"from":"_2","to":"_6"}},{"$":{"from":"_6","to":"_3"}}]}]}}