{"gxl":{"$":{"xmlns:xlink":"http://www.w3.org/1999/xlink"},"graph":[{"$":{"id":"KP1_0076","edgeids":"false","edgemode":"undirected"},"node":[{"$":{"id":"_0"},"attr":[{"$":{"name":"x"},"float":["0.808773"]},{"$":{"name":"y"},"float":["2.81277"]}]},{"$":{"id":"_1"},"attr":[{"$":{"name":"x"},"float":["1.92"]},{"$":{"name":"y"},"float":["2.85"]}]},{"$":{"id":"_2"},"attr":[{"$":{"name":"x"},"float":["0.647376"]},{"$":{"name":"y"},"float":["0.695395"]}]},{"$":{"id":"_3"},"attr":[{"$":{"name":"x"},"float":["0.502597"]},{"$":{"name":"y"},"float":["1.7434"]}]},{"$":{"id":"_4"},"attr":[{"$":{"name":"x"},"float":["2.01431"]},{"$":{"name":"y"},"float":["0.682328"]}]},{"$":{"id":"_5"},"attr":[{"$":{"name":"x"},"float":["1.89733"]},{"$":{"name":"y"},"float":["1.78974"]}]},{"$":{"id":"_6"},"attr":[{"$":{"name":"x"},"float":["0.7414760854920768"]},{"$":{"name":"y"},"float":["1.9298985441723577"]}]},{"$":{"id":"_7"},"attr":[{"$":{"name":"x"},"float":["0.7158506462145902"]},{"$":{"name":"y"},"float":["1.5937171746910905"]}]}],"edge":[{"$":{"from":"_1","to":"_5"}},{"$":{"from":"_0","to":"_6"}},{"$":{"from":"_1","to":"_6"}},{"$":{"from":"_6","to":"_3"}},{"$":{"from":"_3","to":"_7"}},{"$":{"from":"_7","to":"_4"}},{"$":{"from":"_6","to":"_7"}},{"$":{"from":"_7","to":"_2"}}]}]}}