{"gxl":{"$":{"xmlns:xlink":"http://www.w3.org/1999/xlink"},"graph":[{"$":{"id":"KP1_0032","edgeids":"false","edgemode":"undirected"},"node":[{"$":{"id":"_0"},"attr":[{"$":{"name":"x"},"float":["0.691678"]},{"$":{"name":"y"},"float":["2.7783"]}]},{"$":{"id":"_1"},"attr":[{"$":{"name":"x"},"float":["1.91509"]},{"$":{"name":"y"},"float":["2.73846"]}]},{"$":{"id":"_2"},"attr":[{"$":{"name":"x"},"float":["0.663282"]},{"$":{"name":"y"},"float":["0.740876"]}]},{"$":{"id":"_3"},"attr":[{"$":{"name":"x"},"float":["0.568104"]},{"$":{"name":"y"},"float":["1.81886"]}]},{"$":{"id":"_4"},"attr":[{"$":{"name":"x"},"float":["1.91"]},{"$":{"name":"y"},"float":["0.63"]}]},{"$":{"id":"_5"},"attr":[{"$":{"name":"x"},"float":["0.459738"]},{"$":{"name":"y"},"float":["1.52943"]}]},{"$":{"id":"_6"},"attr":[{"$":{"name":"x"},"float":["0.6793647389815577"]},{"$":{"name":"y"},"float":["1.8948187520341269"]}]},{"$":{"id":"_7"},"attr":[{"$":{"name":"x"},"float":["0.6769619362348442"]},{"$":{"name":"y"},"float":["1.7224167241633055"]}]},{"$":{"id":"_8"},"attr":[{"$":{"name":"x"},"float":["0.6724337746909641"]},{"$":{"name":"y"},"float":["1.397519379277473"]}]}],"edge":[{"$":{"from":"_0","to":"_6"}},{"$":{"from":"_1","to":"_6"}},{"$":{"from":"_6","to":"_3"}},{"$":{"from":"_3","to":"_7"}},{"$":{"from":"_7","to":"_4"}},{"$":{"from":"_6","to":"_7"}},{"$":{"from":"_4","to":"_8"}},{"$":{"from":"_8","to":"_5"}},{"$":{"from":"_7","to":"_8"}},{"$":{"from":"_8","to":"_2"}}]}]}}