{"gxl":{"$":{"xmlns:xlink":"http://www.w3.org/1999/xlink"},"graph":[{"$":{"id":"LP1_0055","edgeids":"false","edgemode":"undirected"},"node":[{"$":{"id":"_0"},"attr":[{"$":{"name":"x"},"float":["0.808117"]},{"$":{"name":"y"},"float":["2.84169"]}]},{"$":{"id":"_1"},"attr":[{"$":{"name":"x"},"float":["0.67003"]},{"$":{"name":"y"},"float":["0.663772"]}]},{"$":{"id":"_2"},"attr":[{"$":{"name":"x"},"float":["2.21367"]},{"$":{"name":"y"},"float":["0.559377"]}]}],"edge":[{"$":{"from":"_0","to":"_1"}},{"$":{"from":"_1","to":"_2"}}]}]}}