{"gxl":{"$":{"xmlns:xlink":"http://www.w3.org/1999/xlink"},"graph":[{"$":{"id":"MP1_0125","edgeids":"false","edgemode":"undirected"},"node":[{"$":{"id":"_0"},"attr":[{"$":{"name":"x"},"float":["1.54643"]},{"$":{"name":"y"},"float":["1.60846"]}]},{"$":{"id":"_1"},"attr":[{"$":{"name":"x"},"float":["2.4909"]},{"$":{"name":"y"},"float":["2.9141"]}]},{"$":{"id":"_2"},"attr":[{"$":{"name":"x"},"float":["2.50889"]},{"$":{"name":"y"},"float":["0.582951"]}]},{"$":{"id":"_3"},"attr":[{"$":{"name":"x"},"float":["0.60285"]},{"$":{"name":"y"},"float":["0.525236"]}]},{"$":{"id":"_4"},"attr":[{"$":{"name":"x"},"float":["0.584283"]},{"$":{"name":"y"},"float":["2.99345"]}]}],"edge":[{"$":{"from":"_0","to":"_1"}},{"$":{"from":"_0","to":"_4"}},{"$":{"from":"_1","to":"_2"}},{"$":{"from":"_3","to":"_4"}}]}]}}