{"gxl":{"$":{"xmlns:xlink":"http://www.w3.org/1999/xlink"},"graph":[{"$":{"id":"VP1_0003","edgeids":"false","edgemode":"undirected"},"node":[{"$":{"id":"_0"},"attr":[{"$":{"name":"x"},"float":["0.611981"]},{"$":{"name":"y"},"float":["2.87271"]}]},{"$":{"id":"_1"},"attr":[{"$":{"name":"x"},"float":["1.55974"]},{"$":{"name":"y"},"float":["0.604294"]}]},{"$":{"id":"_2"},"attr":[{"$":{"name":"x"},"float":["2.31521"]},{"$":{"name":"y"},"float":["2.95316"]}]}],"edge":[{"$":{"from":"_0","to":"_1"}},{"$":{"from":"_1","to":"_2"}}]}]}}