{"gxl":{"$":{"xmlns:xlink":"http://www.w3.org/1999/xlink"},"graph":[{"$":{"id":"EP1_0126","edgeids":"false","edgemode":"undirected"},"node":[{"$":{"id":"_0"},"attr":[{"$":{"name":"x"},"float":["2.32472"]},{"$":{"name":"y"},"float":["2.32057"]}]},{"$":{"id":"_1"},"attr":[{"$":{"name":"x"},"float":["2.25"]},{"$":{"name":"y"},"float":["0.71"]}]},{"$":{"id":"_2"},"attr":[{"$":{"name":"x"},"float":["0.987061"]},{"$":{"name":"y"},"float":["0.932615"]}]},{"$":{"id":"_3"},"attr":[{"$":{"name":"x"},"float":["0.959983"]},{"$":{"name":"y"},"float":["2.20757"]}]},{"$":{"id":"_4"},"attr":[{"$":{"name":"x"},"float":["0.765882"]},{"$":{"name":"y"},"float":["2.36962"]}]},{"$":{"id":"_5"},"attr":[{"$":{"name":"x"},"float":["1.29876"]},{"$":{"name":"y"},"float":["1.74635"]}]},{"$":{"id":"_6"},"attr":[{"$":{"name":"x"},"float":["0.86764"]},{"$":{"name":"y"},"float":["1.14579"]}]}],"edge":[{"$":{"from":"_0","to":"_3"}},{"$":{"from":"_1","to":"_2"}},{"$":{"from":"_1","to":"_6"}},{"$":{"from":"_2","to":"_3"}},{"$":{"from":"_4","to":"_5"}}]}]}}