{"gxl":{"$":{"xmlns:xlink":"http://www.w3.org/1999/xlink"},"graph":[{"$":{"id":"HP1_0143","edgeids":"false","edgemode":"undirected"},"node":[{"$":{"id":"_0"},"attr":[{"$":{"name":"x"},"float":["1.27276"]},{"$":{"name":"y"},"float":["2.37395"]}]},{"$":{"id":"_1"},"attr":[{"$":{"name":"x"},"float":["0.327119"]},{"$":{"name":"y"},"float":["1.01703"]}]},{"$":{"id":"_2"},"attr":[{"$":{"name":"x"},"float":["2.06"]},{"$":{"name":"y"},"float":["0.66"]}]},{"$":{"id":"_3"},"attr":[{"$":{"name":"x"},"float":["1.69408"]},{"$":{"name":"y"},"float":["2.54221"]}]},{"$":{"id":"_4"},"attr":[{"$":{"name":"x"},"float":["1.18753"]},{"$":{"name":"y"},"float":["1.97593"]}]},{"$":{"id":"_5"},"attr":[{"$":{"name":"x"},"float":["2.66076"]},{"$":{"name":"y"},"float":["1.44195"]}]},{"$":{"id":"_6"},"attr":[{"$":{"name":"x"},"float":["0.28498"]},{"$":{"name":"y"},"float":["1.26806"]}]}],"edge":[{"$":{"from":"_0","to":"_1"}},{"$":{"from":"_2","to":"_3"}},{"$":{"from":"_2","to":"_6"}},{"$":{"from":"_4","to":"_5"}}]}]}}