{"gxl":{"$":{"xmlns:xlink":"http://www.w3.org/1999/xlink"},"graph":[{"$":{"id":"KP1_0145","edgeids":"false","edgemode":"undirected"},"node":[{"$":{"id":"_0"},"attr":[{"$":{"name":"x"},"float":["0.765268"]},{"$":{"name":"y"},"float":["2.88422"]}]},{"$":{"id":"_1"},"attr":[{"$":{"name":"x"},"float":["1.64101"]},{"$":{"name":"y"},"float":["3.30208"]}]},{"$":{"id":"_2"},"attr":[{"$":{"name":"x"},"float":["0.547032"]},{"$":{"name":"y"},"float":["0.384809"]}]},{"$":{"id":"_3"},"attr":[{"$":{"name":"x"},"float":["0.681378"]},{"$":{"name":"y"},"float":["2.09683"]}]},{"$":{"id":"_4"},"attr":[{"$":{"name":"x"},"float":["1.47066"]},{"$":{"name":"y"},"float":["0.465561"]}]},{"$":{"id":"_5"},"attr":[{"$":{"name":"x"},"float":["0.6983817513993332"]},{"$":{"name":"y"},"float":["2.1181858649295213"]}]},{"$":{"id":"_6"},"attr":[{"$":{"name":"x"},"float":["0.9108523016997733"]},{"$":{"name":"y"},"float":["2.3850382945583846"]}]},{"$":{"id":"_7"},"attr":[{"$":{"name":"x"},"float":["0.6942027111703195"]},{"$":{"name":"y"},"float":["2.070324196287137"]}]}],"edge":[{"$":{"from":"_0","to":"_5"}},{"$":{"from":"_5","to":"_3"}},{"$":{"from":"_0","to":"_6"}},{"$":{"from":"_6","to":"_4"}},{"$":{"from":"_1","to":"_6"}},{"$":{"from":"_6","to":"_5"}},{"$":{"from":"_3","to":"_7"}},{"$":{"from":"_7","to":"_4"}},{"$":{"from":"_5","to":"_7"}},{"$":{"from":"_7","to":"_2"}}]}]}}