{"gxl":{"$":{"xmlns:xlink":"http://www.w3.org/1999/xlink"},"graph":[{"$":{"id":"KP1_0074","edgeids":"false","edgemode":"undirected"},"node":[{"$":{"id":"_0"},"attr":[{"$":{"name":"x"},"float":["0.110803"]},{"$":{"name":"y"},"float":["2.9962"]}]},{"$":{"id":"_1"},"attr":[{"$":{"name":"x"},"float":["2.19599"]},{"$":{"name":"y"},"float":["2.98628"]}]},{"$":{"id":"_2"},"attr":[{"$":{"name":"x"},"float":["0.961439"]},{"$":{"name":"y"},"float":["0.105176"]}]},{"$":{"id":"_3"},"attr":[{"$":{"name":"x"},"float":["0.946779"]},{"$":{"name":"y"},"float":["1.28403"]}]},{"$":{"id":"_4"},"attr":[{"$":{"name":"x"},"float":["1.91"]},{"$":{"name":"y"},"float":["0.63"]}]},{"$":{"id":"_5"},"attr":[{"$":{"name":"x"},"float":["0.171796"]},{"$":{"name":"y"},"float":["1.30573"]}]},{"$":{"id":"_6"},"attr":[{"$":{"name":"x"},"float":["0.6645600663592394"]},{"$":{"name":"y"},"float":["1.1141670634511667"]}]}],"edge":[{"$":{"from":"_1","to":"_3"}},{"$":{"from":"_3","to":"_4"}},{"$":{"from":"_0","to":"_6"}},{"$":{"from":"_6","to":"_2"}},{"$":{"from":"_4","to":"_6"}},{"$":{"from":"_6","to":"_5"}}]}]}}