{"gxl":{"$":{"xmlns:xlink":"http://www.w3.org/1999/xlink"},"graph":[{"$":{"id":"WP1_0134","edgeids":"false","edgemode":"undirected"},"node":[{"$":{"id":"_0"},"attr":[{"$":{"name":"x"},"float":["0.52"]},{"$":{"name":"y"},"float":["2.99"]}]},{"$":{"id":"_1"},"attr":[{"$":{"name":"x"},"float":["0.806639"]},{"$":{"name":"y"},"float":["1.13027"]}]},{"$":{"id":"_2"},"attr":[{"$":{"name":"x"},"float":["2.5"]},{"$":{"name":"y"},"float":["3"]}]},{"$":{"id":"_3"},"attr":[{"$":{"name":"x"},"float":["2.42912"]},{"$":{"name":"y"},"float":["0.124306"]}]},{"$":{"id":"_4"},"attr":[{"$":{"name":"x"},"float":["1.56196"]},{"$":{"name":"y"},"float":["2.31626"]}]},{"$":{"id":"_5"},"attr":[{"$":{"name":"x"},"float":["1.10509"]},{"$":{"name":"y"},"float":["0.649057"]}]},{"$":{"id":"_6"},"attr":[{"$":{"name":"x"},"float":["2.10719"]},{"$":{"name":"y"},"float":["0.698482"]}]}],"edge":[{"$":{"from":"_0","to":"_1"}},{"$":{"from":"_0","to":"_5"}},{"$":{"from":"_1","to":"_4"}},{"$":{"from":"_2","to":"_3"}},{"$":{"from":"_2","to":"_6"}},{"$":{"from":"_3","to":"_4"}}]}]}}