{"gxl":{"$":{"xmlns:xlink":"http://www.w3.org/1999/xlink"},"graph":[{"$":{"id":"YP1_0000","edgeids":"false","edgemode":"undirected"},"node":[{"$":{"id":"_0"},"attr":[{"$":{"name":"x"},"float":["0.448359"]},{"$":{"name":"y"},"float":["3.16094"]}]},{"$":{"id":"_1"},"attr":[{"$":{"name":"x"},"float":["1.15498"]},{"$":{"name":"y"},"float":["2.30748"]}]},{"$":{"id":"_2"},"attr":[{"$":{"name":"x"},"float":["1.14479"]},{"$":{"name":"y"},"float":["0.464185"]}]},{"$":{"id":"_3"},"attr":[{"$":{"name":"x"},"float":["3.06969"]},{"$":{"name":"y"},"float":["3.1438"]}]}],"edge":[{"$":{"from":"_0","to":"_1"}},{"$":{"from":"_1","to":"_2"}},{"$":{"from":"_1","to":"_3"}}]}]}}