{"gxl":{"$":{"xmlns:xlink":"http://www.w3.org/1999/xlink"},"graph":[{"$":{"id":"YP1_0006","edgeids":"false","edgemode":"undirected"},"node":[{"$":{"id":"_0"},"attr":[{"$":{"name":"x"},"float":["0.0803979"]},{"$":{"name":"y"},"float":["2.96065"]}]},{"$":{"id":"_1"},"attr":[{"$":{"name":"x"},"float":["1.82436"]},{"$":{"name":"y"},"float":["1.99814"]}]},{"$":{"id":"_2"},"attr":[{"$":{"name":"x"},"float":["1.11778"]},{"$":{"name":"y"},"float":["0.863967"]}]},{"$":{"id":"_3"},"attr":[{"$":{"name":"x"},"float":["2.31872"]},{"$":{"name":"y"},"float":["3.64299"]}]}],"edge":[{"$":{"from":"_0","to":"_1"}},{"$":{"from":"_1","to":"_2"}},{"$":{"from":"_1","to":"_3"}}]}]}}